awssso/__awssso.py
awssso/__init__.py
py_aws_sso-0.1.1.dist-info/METADATA
py_aws_sso-0.1.1.dist-info/WHEEL
py_aws_sso-0.1.1.dist-info/licenses/LICENSE
py_aws_sso-0.1.1.dist-info/RECORD
