Metadata-Version: 2.1
Name: py-aws-sso
Version: 0.1.1
Summary: Simple Python library for AWS SSO credential management in local development.
Author: Pritam
License: MIT
Requires-Python: >=3.10
Requires-Dist: boto3>=1.34.117
